timchen/__init__.py
timchen-0.0.3.dist-info/LICENCE
timchen-0.0.3.dist-info/METADATA
timchen-0.0.3.dist-info/WHEEL
timchen-0.0.3.dist-info/top_level.txt
timchen-0.0.3.dist-info/RECORD
