Metadata-Version: 2.1
Name: timchen
Version: 0.0.3
Summary: Timchen
Home-page: https://repl.it/@mat1
Author: mat
Author-email: fake@email.lol
License: UNKNOWN
Platform: UNKNOWN
Classifier: Programming Language :: Python :: 3
Classifier: License :: OSI Approved :: MIT License
Classifier: Operating System :: OS Independent
Requires-Dist: aiohttp
